LICENSE
job_runner/__init__.py
job_runner/apps.py
job_runner/environment.py
job_runner/management/commands/run_jobs.py
job_runner/migrations/__init__.py
job_runner/registration.py
job_runner/runner.py
job_runner/sample_jobs.py
job_runner/test_management_command.py
job_runner/test_time.py
job_runner/test_timeout.py
job_runner/test_tracker.py
job_runner/time.py
job_runner/timeouts.py
django_quick_jobs-0.4.0.dist-info/LICENSE
django_quick_jobs-0.4.0.dist-info/WHEEL
django_quick_jobs-0.4.0.dist-info/METADATA
django_quick_jobs-0.4.0.dist-info/RECORD
