Metadata-Version: 2.1
Name: django-quick-jobs
Version: 0.4.0
Summary: A method of quickly and simply running background jobs in a Django project
Home-page: https://github.com/Hovercross/django-quick-jobs
License: MIT
Keywords: django,tasks,background
Author: Adam Peacock
Author-email: adam@thepeacock.net
Requires-Python: >=3.7,<4.0
Classifier: Development Status :: 4 - Beta
Classifier: Framework :: Django
Classifier: Intended Audience :: Developers
Classifier: License :: OSI Approved :: MIT License
Classifier: Operating System :: OS Independent
Classifier: Programming Language :: Python :: 3
Classifier: Programming Language :: Python :: 3.10
Classifier: Programming Language :: Python :: 3.7
Classifier: Programming Language :: Python :: 3.8
Classifier: Programming Language :: Python :: 3.9
Requires-Dist: Django (>=2.2)
Requires-Dist: structlog
Project-URL: Repository, https://github.com/Hovercross/django-quick-jobs
